obniz_cli.py
commands/__init__.py
commands/eraseos.py
commands/flashos.py
commands/util.py
obniz_cli_/__init__.py
obniz_cli_/__version__.py
obniz_cli-0.0.6.dist-info/METADATA
obniz_cli-0.0.6.dist-info/WHEEL
obniz_cli-0.0.6.dist-info/entry_points.txt
obniz_cli-0.0.6.dist-info/top_level.txt
obniz_cli-0.0.6.dist-info/RECORD
