Metadata-Version: 2.1
Name: obniz-cli
Version: 0.0.6
Summary: cli tool for obnizOS setup
Home-page: UNKNOWN
License: UNKNOWN
Platform: UNKNOWN
Requires-Dist: esptool
Requires-Dist: requests
